NiukeJishuGangBibeiBiMianshiSuanfa/README.md
NiukeJishuGangBibeiBiMianshiSuanfa/__init__.py
NiukeJishuGangBibeiBiMianshiSuanfa/__main__.py
NiukeJishuGangBibeiBiMianshiSuanfa/file.epub
NiukeJishuGangBibeiBiMianshiSuanfa/index.html
NiukeJishuGangBibeiBiMianshiSuanfa/css/__init__.py
NiukeJishuGangBibeiBiMianshiSuanfa/css/annotations.css
NiukeJishuGangBibeiBiMianshiSuanfa/css/main.css
NiukeJishuGangBibeiBiMianshiSuanfa/css/normalize.css
NiukeJishuGangBibeiBiMianshiSuanfa/css/popup.css
NiukeJishuGangBibeiBiMianshiSuanfa/font/__init__.py
NiukeJishuGangBibeiBiMianshiSuanfa/font/fontello.eot
NiukeJishuGangBibeiBiMianshiSuanfa/font/fontello.svg
NiukeJishuGangBibeiBiMianshiSuanfa/font/fontello.ttf
NiukeJishuGangBibeiBiMianshiSuanfa/font/fontello.woff
NiukeJishuGangBibeiBiMianshiSuanfa/img/__init__.py
NiukeJishuGangBibeiBiMianshiSuanfa/img/annotator-glyph-sprite.png
NiukeJishuGangBibeiBiMianshiSuanfa/img/annotator-icon-sprite.png
NiukeJishuGangBibeiBiMianshiSuanfa/img/apple-touch-icon.png
NiukeJishuGangBibeiBiMianshiSuanfa/img/cancelfullscreen.png
NiukeJishuGangBibeiBiMianshiSuanfa/img/close.png
NiukeJishuGangBibeiBiMianshiSuanfa/img/fullscreen.png
NiukeJishuGangBibeiBiMianshiSuanfa/img/loader.gif
NiukeJishuGangBibeiBiMianshiSuanfa/img/menu-icon.png
NiukeJishuGangBibeiBiMianshiSuanfa/img/save.png
NiukeJishuGangBibeiBiMianshiSuanfa/img/saved.png
NiukeJishuGangBibeiBiMianshiSuanfa/img/settings-s.png
NiukeJishuGangBibeiBiMianshiSuanfa/img/settings.png
NiukeJishuGangBibeiBiMianshiSuanfa/img/star.png
NiukeJishuGangBibeiBiMianshiSuanfa/js/__init__.py
NiukeJishuGangBibeiBiMianshiSuanfa/js/epub.js
NiukeJishuGangBibeiBiMianshiSuanfa/js/epub.min.js
NiukeJishuGangBibeiBiMianshiSuanfa/js/epub.min.map
NiukeJishuGangBibeiBiMianshiSuanfa/js/hooks.min.js
NiukeJishuGangBibeiBiMianshiSuanfa/js/hooks.min.map
NiukeJishuGangBibeiBiMianshiSuanfa/js/reader.js
NiukeJishuGangBibeiBiMianshiSuanfa/js/reader.js.map
NiukeJishuGangBibeiBiMianshiSuanfa/js/reader.min.js
niuke_jishu_gang_bibei_bi_mianshi_suanfa-2024.3.6.0.dist-info/METADATA
niuke_jishu_gang_bibei_bi_mianshi_suanfa-2024.3.6.0.dist-info/WHEEL
niuke_jishu_gang_bibei_bi_mianshi_suanfa-2024.3.6.0.dist-info/entry_points.txt
niuke_jishu_gang_bibei_bi_mianshi_suanfa-2024.3.6.0.dist-info/top_level.txt
niuke_jishu_gang_bibei_bi_mianshi_suanfa-2024.3.6.0.dist-info/RECORD
